CHANGELOG.rst
LICENSE.md
MANIFEST.in
README.rst
setup.cfg
setup.py
src/PyORAM.egg-info/PKG-INFO
src/PyORAM.egg-info/SOURCES.txt
src/PyORAM.egg-info/dependency_links.txt
src/PyORAM.egg-info/requires.txt
src/PyORAM.egg-info/top_level.txt
src/_cffi_src/__init__.py
src/_cffi_src/virtual_heap_helper_build.py
src/pyoram/__about__.py
src/pyoram/__init__.py
src/pyoram/crypto/__init__.py
src/pyoram/crypto/aes.py
src/pyoram/encrypted_storage/__init__.py
src/pyoram/encrypted_storage/encrypted_block_storage.py
src/pyoram/encrypted_storage/encrypted_heap_storage.py
src/pyoram/encrypted_storage/top_cached_encrypted_heap_storage.py
src/pyoram/oblivious_storage/__init__.py
src/pyoram/oblivious_storage/tree/__init__.py
src/pyoram/oblivious_storage/tree/path_oram.py
src/pyoram/oblivious_storage/tree/tree_oram_helper.py
src/pyoram/storage/__init__.py
src/pyoram/storage/block_storage.py
src/pyoram/storage/block_storage_file.py
src/pyoram/storage/block_storage_mmap.py
src/pyoram/storage/block_storage_ram.py
src/pyoram/storage/block_storage_s3.py
src/pyoram/storage/block_storage_sftp.py
src/pyoram/storage/boto3_s3_wrapper.py
src/pyoram/storage/heap_storage.py
src/pyoram/tests/__init__.py
src/pyoram/tests/test_aes.py
src/pyoram/tests/test_block_storage.py
src/pyoram/tests/test_encrypted_block_storage.py
src/pyoram/tests/test_encrypted_heap_storage.py
src/pyoram/tests/test_examples.py
src/pyoram/tests/test_misc.py
src/pyoram/tests/test_package.py
src/pyoram/tests/test_path_oram.py
src/pyoram/tests/test_top_cached_encrypted_heap_storage.py
src/pyoram/tests/test_virtual_heap.py
src/pyoram/util/__init__.py
src/pyoram/util/misc.py
src/pyoram/util/virtual_heap.py