Metadata-Version: 1.1
Name: PyORAM
Version: 0.1.2
Summary: Python-based Oblivious RAM
Home-page: https://github.com/ghackebeil/PyORAM
Author: Gabriel A. Hackebeil
Author-email: gabe.hackebeil@gmail.com
License: MIT
Keywords: oram,storage,privacy,cryptography,cloud storage
Platform: UNKNOWN
Classifier: Development Status :: 4 - Beta
Classifier: Intended Audience :: Science/Research
Classifier: Topic :: Security :: Cryptography
Classifier: Natural Language :: English
Classifier: License :: OSI Approved :: MIT License
Classifier: Programming Language :: Python :: 2.7
Classifier: Programming Language :: Python :: 3
Classifier: Programming Language :: Python :: 3.3
Classifier: Programming Language :: Python :: 3.4
Classifier: Programming Language :: Python :: 3.5
Classifier: Programming Language :: Python :: Implementation :: CPython
Classifier: Programming Language :: Python :: Implementation :: PyPy
